{"v":"5.4.2","fr":60,"ip":0,"op":60,"w":358,"h":123,"nm":"beyondX_punch_cut_camera_switch_effect _invert","ddd":0,"assets":[{"id":"comp_0","layers":[{"ddd":0,"ind":1,"ty":1,"nm":"L","td":1,"sr":1,"ks":{"o":{"a":0,"k":100,"ix":11},"r":{"a":0,"k":45,"ix":10},"p":{"a":1,"k":[{"i":{"x":0.2,"y":1},"o":{"x":0.33,"y":0},"n":"0p2_1_0p33_0","t":0,"s":[-51.5,62.548,0],"e":[473.5,62.548,0],"to":[0,0,0],"ti":[0,0,0]},{"t":60}],"ix":2},"a":{"a":0,"k":[24,135,0],"ix":1},"s":{"a":0,"k":[100,100,100],"ix":6}},"ao":0,"sw":48,"sh":270,"sc":"#ffffff","ip":0,"op":4000,"st":0,"bm":0},{"ddd":0,"ind":2,"ty":4,"nm":"cue_14","tt":1,"sr":1,"ks":{"o":{"a":0,"k":100,"ix":11},"r":{"a":0,"k":0,"ix":10},"p":{"a":0,"k":[179.201,61.796,0],"ix":2},"a":{"a":0,"k":[520.52,-1431.188,0],"ix":1},"s":{"a":1,"k":[{"i":{"x":[0.84,0.84,0.84],"y":[1.752,0.863,4.382]},"o":{"x":[0.33,0.33,0.33],"y":[0,0,0]},"n":["0p84_1p752_0p33_0","0p84_0p863_0p33_0","0p84_4p382_0p33_0"],"t":9,"s":[-85,85,100],"e":[-80.5,60.4,100]},{"t":71}],"ix":6}},"ao":0,"shapes":[{"ty":"gr","it":[{"ind":0,"ty":"sh","ix":1,"ks":{"a":0,"k":{"i":[[-28.443,0],[0,0],[0,-28.443],[0,0],[36.316,0.952],[0,0],[0,28.443],[0,0]],"o":[[0,0],[34.51,-0.291],[0,0],[0,28.443],[0,0],[-32.596,-0.348],[0,0],[0,-28.443]],"v":[[-193.275,-64.342],[78.989,-64.401],[140.676,-4.935],[140.676,1.066],[78.654,63.547],[-193.61,63.239],[-251.471,0.894],[-251.471,-5.106]],"c":true},"ix":2},"nm":"Path 1","mn":"ADBE Vector Shape - Group","hd":false},{"ty":"st","c":{"a":0,"k":[0,0,0,1],"ix":3},"o":{"a":0,"k":100,"ix":4},"w":{"a":0,"k":8,"ix":5},"lc":2,"lj":1,"ml":4,"ml2":{"a":0,"k":4,"ix":8},"nm":"Stroke 1","mn":"ADBE Vector Graphic - Stroke","hd":false},{"ty":"tr","p":{"a":0,"k":[575.5,-1430.5],"ix":2},"a":{"a":0,"k":[0,0],"ix":1},"s":{"a":0,"k":[100,100],"ix":3},"r":{"a":0,"k":0,"ix":6},"o":{"a":0,"k":100,"ix":7},"sk":{"a":0,"k":0,"ix":4},"sa":{"a":0,"k":0,"ix":5},"nm":"Transform"}],"nm":"Ellipse 1","np":2,"cix":2,"ix":1,"mn":"ADBE Vector Group","hd":false},{"ty":"tm","s":{"a":0,"k":0,"ix":1},"e":{"a":0,"k":100,"ix":2},"o":{"a":0,"k":-62,"ix":3},"m":1,"ix":2,"nm":"Trim Paths 1","mn":"ADBE Vector Filter - Trim","hd":false}],"ip":0,"op":123,"st":-125,"bm":0},{"ddd":0,"ind":3,"ty":4,"nm":"cue_13","sr":1,"ks":{"o":{"a":0,"k":30,"ix":11},"r":{"a":0,"k":0,"ix":10},"p":{"a":0,"k":[179.201,61.796,0],"ix":2},"a":{"a":0,"k":[520.52,-1431.188,0],"ix":1},"s":{"a":1,"k":[{"i":{"x":[0.84,0.84,0.84],"y":[1.752,0.863,4.382]},"o":{"x":[0.33,0.33,0.33],"y":[0,0,0]},"n":["0p84_1p752_0p33_0","0p84_0p863_0p33_0","0p84_4p382_0p33_0"],"t":9,"s":[-85,85,100],"e":[-80.5,60.4,100]},{"t":71}],"ix":6}},"ao":0,"shapes":[{"ty":"gr","it":[{"ind":0,"ty":"sh","ix":1,"ks":{"a":0,"k":{"i":[[-28.443,0],[0,0],[0,-28.443],[0,0],[36.316,0.952],[0,0],[0,28.443],[0,0]],"o":[[0,0],[34.51,-0.291],[0,0],[0,28.443],[0,0],[-32.596,-0.348],[0,0],[0,-28.443]],"v":[[-193.275,-64.342],[78.989,-64.401],[140.676,-4.935],[140.676,1.066],[78.654,63.547],[-193.61,63.239],[-251.471,0.894],[-251.471,-5.106]],"c":true},"ix":2},"nm":"Path 1","mn":"ADBE Vector Shape - Group","hd":false},{"ty":"st","c":{"a":0,"k":[0,0,0,1],"ix":3},"o":{"a":0,"k":100,"ix":4},"w":{"a":0,"k":8,"ix":5},"lc":2,"lj":1,"ml":4,"ml2":{"a":0,"k":4,"ix":8},"nm":"Stroke 1","mn":"ADBE Vector Graphic - Stroke","hd":false},{"ty":"tr","p":{"a":0,"k":[575.5,-1430.5],"ix":2},"a":{"a":0,"k":[0,0],"ix":1},"s":{"a":0,"k":[100,100],"ix":3},"r":{"a":0,"k":0,"ix":6},"o":{"a":0,"k":100,"ix":7},"sk":{"a":0,"k":0,"ix":4},"sa":{"a":0,"k":0,"ix":5},"nm":"Transform"}],"nm":"Ellipse 1","np":2,"cix":2,"ix":1,"mn":"ADBE Vector Group","hd":false},{"ty":"tm","s":{"a":0,"k":0,"ix":1},"e":{"a":0,"k":100,"ix":2},"o":{"a":0,"k":-62,"ix":3},"m":1,"ix":2,"nm":"Trim Paths 1","mn":"ADBE Vector Filter - Trim","hd":false}],"ip":0,"op":123,"st":-125,"bm":0}]}],"layers":[{"ddd":0,"ind":2,"ty":4,"nm":"Shape Layer 3","td":1,"sr":1,"ks":{"o":{"a":0,"k":100,"ix":11},"r":{"a":0,"k":0,"ix":10},"p":{"a":0,"k":[179.201,61.796,0],"ix":2},"a":{"a":0,"k":[519.937,-1431.221,0],"ix":1},"s":{"a":0,"k":[85,85,100],"ix":6}},"ao":0,"shapes":[{"ty":"gr","it":[{"ind":0,"ty":"sh","ix":1,"ks":{"a":0,"k":{"i":[[-28.443,0],[0,0],[0,-27.491],[0,0],[34.923,0],[0,0],[0,28.443],[0,0]],"o":[[0,0],[31.01,0],[0,0],[0,27.097],[0,0],[-31.636,0],[0,0],[0,-28.443]],"v":[[388.152,-1490.656],[651.298,-1490.648],[712.426,-1435.402],[712.426,-1429.402],[651.248,-1371.45],[387.881,-1371.366],[328.239,-1429.672],[328.239,-1435.672]],"c":true},"ix":2},"nm":"Path 1","mn":"ADBE Vector Shape - Group","hd":false},{"ty":"fl","c":{"a":0,"k":[0,0,0,1],"ix":4},"o":{"a":0,"k":100,"ix":5},"r":1,"nm":"Fill 1","mn":"ADBE Vector Graphic - Fill","hd":false},{"ty":"tr","p":{"a":0,"k":[0,0],"ix":2},"a":{"a":0,"k":[0,0],"ix":1},"s":{"a":0,"k":[100,100],"ix":3},"r":{"a":0,"k":0,"ix":6},"o":{"a":0,"k":100,"ix":7},"sk":{"a":0,"k":0,"ix":4},"sa":{"a":0,"k":0,"ix":5},"nm":"Transform"}],"nm":"Shape 1","np":3,"cix":2,"ix":1,"mn":"ADBE Vector Group","hd":false}],"ip":-36,"op":6564,"st":-36,"bm":0},{"ddd":0,"ind":3,"ty":0,"nm":"beyondX_effect_precomp2_invert","tt":2,"refId":"comp_0","sr":1,"ks":{"o":{"a":0,"k":100,"ix":11},"r":{"a":0,"k":0,"ix":10},"p":{"a":0,"k":[179,61.5,0],"ix":2},"a":{"a":0,"k":[179,61.5,0],"ix":1},"s":{"a":0,"k":[100,100,100],"ix":6}},"ao":0,"w":358,"h":123,"ip":0,"op":4000,"st":0,"bm":0}],"markers":[]}